[
    {
        "imgsrc": null,
        "name": "Transparent Head Protector Blueprint",
        "chineseName": "潜水头盔图纸",
        "description": "",
        "effect": ""
    },
    {
        "imgsrc": null,
        "name": "Transparent Head Protector Blueprint",
        "chineseName": "潜水头盔图纸",
        "description": "",
        "effect": ""
    },
    {
        "imgsrc": "s01.cdn.roguard.net/content/img/icons/items/item_45017.png",
        "name": "Transparent Head Protector [1]",
        "chineseName": "潜水头盔[1]",
        "description": "A round dome that protects the head. It's made of magic materials and allows the wearer to breathe, unlike one made of other materials.",
        "effect": ""
    },
    {
        "imgsrc": null,
        "name": "Transparent Head Protector [1]",
        "chineseName": "潜水头盔[1]",
        "description": "",
        "effect": "Dex ＋3,AGI ＋3"
    },
    {
        "imgsrc": "s01.cdn.roguard.net/content/img/icons/items/item_45017.png",
        "name": "Transparent Head Protector [1] Blueprint",
        "chineseName": "潜水头盔[1]图纸",
        "description": "A round dome that protects the head. It's made of magic materials and allows the wearer to breathe, unlike one made of other materials.",
        "effect": ""
    },
    {
        "imgsrc": null,
        "name": "Transparent Wing Blueprint",
        "chineseName": "透明翅膀图纸",
        "description": "Faith of countless people materialized into these wings. They are invisible to the faithless~",
        "effect": ""
    },
    {
        "imgsrc": null,
        "name": "Transparent Wing Blueprint",
        "chineseName": "透明翅膀",
        "description": "Faith of countless people materialized into these wings. They are invisible to the faithless~",
        "effect": "Max HP ＋300,M.Atk ＋40"
    },
    {
        "imgsrc": null,
        "name": "Tree Crown",
        "chineseName": "树冠",
        "description": "Tree Crown.",
        "effect": ""
    },
    {
        "imgsrc": null,
        "name": "Trick or treat",
        "chineseName": "不给糖就捣蛋",
        "description": "Candy, Cookie, Macaron, Dried fruit, Cake, Donut, Strawberry parfait, Rose black tea, Sakura cola... Ah... Wait... Nothing else...",
        "effect": ""
    },
    {
        "imgsrc": null,
        "name": "Trick or Treat Blueprint",
        "chineseName": "不给糖就捣蛋图纸",
        "description": "",
        "effect": ""
    },
    {
        "imgsrc": "s01.cdn.roguard.net/content/img/icons/items/item_40004.png",
        "name": "Trident",
        "chineseName": "德瑞尹长矛",
        "description": "The long halberd used for hunting is characterized by three blades.",
        "effect": ""
    },
    {
        "imgsrc": "s01.cdn.roguard.net/content/img/icons/items/item_40004.png",
        "name": "Trident [3]",
        "chineseName": "德瑞尹长矛[3]",
        "description": "The long halberd used for hunting is characterized by three blades.",
        "effect": ""
    },
    {
        "imgsrc": null,
        "name": "Tropical Coconut",
        "chineseName": "热带椰子",
        "description": "Coconut peddlers by the sea believe that wearing this headwear will boost fortunes.",
        "effect": ""
    },
    {
        "imgsrc": null,
        "name": "Troublemaker's Candy Box",
        "chineseName": "捣蛋鬼的糖果盒",
        "description": "Alright, Take the candy box. Don't tease me around, You troublemakers. (The candy box from the baron will give you common Halloween candies and snacks in the households.)",
        "effect": ""
    },
    {
        "imgsrc": "s01.cdn.roguard.net/content/img/icons/items/item_700006.png",
        "name": "True Love Chocolate",
        "chineseName": "真命巧克力",
        "description": "The chocolate symbolizing love and purity, it must be made of special materials and the blessing of God of Love from Big Cat planet. Due to the specialty, it can only be sent to the most special person! (Choose the one you love, bravely give it to her/him! Effects: Use it on other adventures, making them receive special displaying effect, restore 520 points of HP every 30 seconds, receive 25 more points of All Attributes; the effect lasts for 12 hours, and will not be affected by death or network failure, and cannot stack up.)",
        "effect": ""
    },
    {
        "imgsrc": "s01.cdn.roguard.net/content/img/icons/items/item_700006.png",
        "name": "True love Chocolate",
        "chineseName": "本命巧克力",
        "description": "The chocolate symbolizing love and purity, it must be made of special materials and the blessing of God of Love from Big Cat planet. Due to the specialty, it can only be sent to the most special person! (Choose the one you love, bravely give it to her/him! Effects: Use it on other adventures, granting them the perfume's effect and restoring 520 HP every 30 seconds. The effect lasts for 12 hours, and will not be affected by death or going offline. Does not stack. )",
        "effect": ""
    },
    {
        "imgsrc": "s01.cdn.roguard.net/content/img/icons/items/item_40301.png",
        "name": "Tsurugi",
        "chineseName": "日本刀",
        "description": "A very frightening and sharp sword used specifically to hurt enemies.",
        "effect": ""
    },
    {
        "imgsrc": "s01.cdn.roguard.net/content/img/icons/items/item_41504.png",
        "name": "Tuna [2]",
        "chineseName": "鲔鱼权杖[2]",
        "description": "A common edible fish. Migrating fishes. It is silver gray on both sides, Dark blue on the back, and white on the fish belly. The body is spindle shaped. The caudal fin is small, Powerful, Crescent shaped, and tasty. It is very hard since it's frozen.",
        "effect": ""
    },
    {
        "imgsrc": "s01.cdn.roguard.net/content/img/icons/items/item_41504.png",
        "name": "Tuna [3]",
        "chineseName": "鲔鱼权杖[3]",
        "description": "A common edible fish. Migrating fishes. It is silver gray on both sides, Dark blue on the back, and white on the fish belly. The body is spindle shaped. The caudal fin is small, Powerful, Crescent shaped, and tasty. It is very hard since it's frozen.",
        "effect": ""
    },
    {
        "imgsrc": "s01.cdn.roguard.net/content/img/icons/items/item_45092.png",
        "name": "Turban",
        "chineseName": "圆帽",
        "description": "Round hat. It makes users look cuter.",
        "effect": ""
    }
]