[
    {
        "imgsrc": null,
        "name": "Love Autumn",
        "slot": "Head",
        "status": "Max HP ＋100"
    },
    {
        "imgsrc": null,
        "name": "Love Beach Mirror",
        "slot": "Face",
        "status": "Max SP ＋50"
    },
    {
        "imgsrc": null,
        "name": "Love Blush",
        "slot": "Face",
        "status": "Max HP ＋50"
    },
    {
        "imgsrc": null,
        "name": "Love Cake",
        "slot": "Head",
        "status": "MAX HP ＋200, HP Regen ＋10%, SP Regen ＋3"
    },
    {
        "imgsrc": null,
        "name": "Love Cake [1]",
        "slot": "Head",
        "status": "MAX HP ＋200, HP Regen ＋10%, SP Regen ＋3"
    },
    {
        "imgsrc": null,
        "name": "Love Goddess",
        "slot": "Wing",
        "status": "Your own damage increases by 10%, but all damage you suffer increases by 20%"
    },
    {
        "imgsrc": null,
        "name": "Love Heart Autumn",
        "slot": "Wing",
        "status": "Max SP ＋100"
    },
    {
        "imgsrc": null,
        "name": "Love Heart Spring",
        "slot": "Wing",
        "status": "Max SP ＋100"
    },
    {
        "imgsrc": null,
        "name": "Love Heart Summer",
        "slot": "Wing",
        "status": "Max SP ＋100"
    },
    {
        "imgsrc": null,
        "name": "Love Heart Winter",
        "slot": "Head",
        "status": "Max SP ＋100"
    },
    {
        "imgsrc": null,
        "name": "Love in your eyes",
        "slot": "Face",
        "status": "Max SP ＋50, Atk ＋10"
    },
    {
        "imgsrc": null,
        "name": "Love of the Tokyo Iron Tower",
        "slot": "Head",
        "status": "All Attributes ＋1, Max SP ＋50"
    },
    {
        "imgsrc": null,
        "name": "Love Spring",
        "slot": "Head",
        "status": "Max HP ＋100"
    },
    {
        "imgsrc": null,
        "name": "Love Summer",
        "slot": "Head",
        "status": "Max HP ＋100"
    },
    {
        "imgsrc": null,
        "name": "Love Winter",
        "slot": "Mouth",
        "status": "Max HP ＋100"
    },
    {
        "imgsrc": null,
        "name": "Love Witch Hat",
        "slot": "Head",
        "status": "All Attributes ＋2, Atk ＋12, M.Atk ＋12"
    },
    {
        "imgsrc": null,
        "name": "Love You",
        "slot": "Mouth",
        "status": "Ignore Def ＋5%, Atk ＋20"
    },
    {
        "imgsrc": null,
        "name": "Loving Butterfly",
        "slot": "Face",
        "status": "Move Spd ＋3%, Luk ＋5, Atk ＋20"
    },
    {
        "imgsrc": "s01.cdn.roguard.net/content/img/icons/items/item_42002.png",
        "name": "Lucius's Fierce Armor of Volcano",
        "slot": "Armour",
        "status": "Def + 42"
    },
    {
        "imgsrc": "s01.cdn.roguard.net/content/img/icons/items/item_42002.png",
        "name": "Lucius's Fierce Armor of Volcano [1]",
        "slot": "Armour",
        "status": "Def + 42"
    }
]