[
    {
        "imgsrc": "s01.cdn.roguard.net/content/img/icons/items/item_45061.png",
        "name": "Succubus Horn [1]",
        "slot": "Head",
        "status": "Def ＋5, INT ＋1, M.Def ＋10"
    },
    {
        "imgsrc": null,
        "name": "Summer baseball cap·Green",
        "slot": "Head",
        "status": "MAX HP ＋400, Def ＋5%"
    },
    {
        "imgsrc": null,
        "name": "Summer baseball cap·Ocean Blue",
        "slot": "Head",
        "status": "MAX HP ＋400, Def ＋5%"
    },
    {
        "imgsrc": null,
        "name": "Summer baseball cap·Red",
        "slot": "Head",
        "status": "MAX HP ＋400, Def ＋5%"
    },
    {
        "imgsrc": null,
        "name": "Summer baseball cap·Yellow",
        "slot": "Head",
        "status": "MAX HP ＋400, Def ＋5%"
    },
    {
        "imgsrc": null,
        "name": "Summer Cap·Green",
        "slot": "Head",
        "status": "MAX HP ＋400, MDef ＋5%"
    },
    {
        "imgsrc": null,
        "name": "Summer Cap·Ocean blue",
        "slot": "Head",
        "status": "MAX HP ＋400, MDef ＋5%"
    },
    {
        "imgsrc": null,
        "name": "Summer Cap·Red",
        "slot": "Head",
        "status": "MAX HP ＋400, MDef ＋5%"
    },
    {
        "imgsrc": null,
        "name": "Summer Cap·Yellow",
        "slot": "Head",
        "status": "MAX HP ＋400, MDef ＋5%"
    },
    {
        "imgsrc": null,
        "name": "Summer Costume",
        "slot": "Armour",
        "status": ""
    },
    {
        "imgsrc": null,
        "name": "Summer Headwear series",
        "slot": "Head",
        "status": "MAX HP ＋400, Def ＋5%"
    },
    {
        "imgsrc": null,
        "name": "Summer Headwear series",
        "slot": "Head",
        "status": "MAX HP ＋400, MDef ＋5%"
    },
    {
        "imgsrc": null,
        "name": "Summer Night Crown",
        "slot": "Head",
        "status": "Dex ＋3, AGI ＋3"
    },
    {
        "imgsrc": null,
        "name": "Summer Penguin",
        "slot": "Head",
        "status": "Max HP ＋100"
    },
    {
        "imgsrc": null,
        "name": "Summoner Coat",
        "slot": "Armour",
        "status": "Dex ＋2, Max SP ＋60"
    },
    {
        "imgsrc": null,
        "name": "Summoner Coat [1]",
        "slot": "Armour",
        "status": "Dex ＋2, Max SP ＋60"
    },
    {
        "imgsrc": null,
        "name": "Sun Back Headwear",
        "slot": "Wing",
        "status": "Max HP ＋3000, Def ＋5%, MDef ＋15%, Crit Res＋8,  Fire, Water, Earth, Wind damage taken -10%"
    },
    {
        "imgsrc": null,
        "name": "Sun God Back Headwear",
        "slot": "Wing",
        "status": "Max HP ＋4000, Def ＋5%, MDef ＋15%, Crit Res＋15,  Poison, Holy, Dark, Ghost, Neutral damage taken -5%, Fire, Water, Earth and Wind damage taken -15%, Gain passive skill [Solar Counter]: When you’re hit, deals (Atk ＋ M.Atk)*30% Real Damage to the attacker."
    },
    {
        "imgsrc": null,
        "name": "Sun Hat",
        "slot": "Head",
        "status": "Max HP ＋3000, Def ＋15%, MDef ＋5%, Crit Res ＋8,  Poison, Holy, Dark, Ghost, Neutral damage taken -10%"
    },
    {
        "imgsrc": "s01.cdn.roguard.net/content/img/icons/items/item_45066.png",
        "name": "Sunday Hat",
        "slot": "Head",
        "status": "M.Def ＋10, CT Variable -5%, When Refining 10, CT Variable -15%"
    }
]